aws_configure/__init__.py
aws_configure/cli.py
aws_configure-2.1.7.dist-info/METADATA
aws_configure-2.1.7.dist-info/WHEEL
aws_configure-2.1.7.dist-info/entry_points.txt
aws_configure-2.1.7.dist-info/top_level.txt
aws_configure-2.1.7.dist-info/RECORD
